authx_extra/__init__.py
authx_extra/cache.py
authx_extra/metrics.py
authx_extra/oauth2.py
authx_extra/profiler.py
authx_extra/session.py
authx_extra/addons/__init__.py
authx_extra/addons/expiry.py
authx_extra/addons/keys.py
authx_extra/extra/__init__.py
authx_extra/extra/_cache.py
authx_extra-1.1.4.dist-info/METADATA
authx_extra-1.1.4.dist-info/WHEEL
authx_extra-1.1.4.dist-info/licenses/LICENSE
authx_extra-1.1.4.dist-info/RECORD
