Metadata-Version: 2.3
Name: authx_extra
Version: 1.1.4
Summary: Extra utilities for authx, including session, profiler & caching ✨
Project-URL: Homepage, https://github.com/yezz123/authx_extra
Project-URL: Documentation, https://authx.yezz.me/installation/#extra-dependencies
Project-URL: Funding, https://github.com/sponsors/yezz123
Author-email: Yasser Tahiri <hello@yezz.me>
License-Expression: MIT
License-File: LICENSE
Keywords: Authentication,Cookie,FastAPI,JWT,Oauth2,Pydantic
Classifier: Development Status :: 5 - Production/Stable
Classifier: Framework :: AsyncIO
Classifier: Framework :: FastAPI
Classifier: Framework :: Pydantic
Classifier: Framework :: Pydantic :: 2
Classifier: Intended Audience :: Developers
Classifier: Intended Audience :: Information Technology
Classifier: License :: OSI Approved :: MIT License
Classifier: Operating System :: OS Independent
Classifier: Programming Language :: Python
Classifier: Programming Language :: Python :: 3
Classifier: Programming Language :: Python :: 3 :: Only
Classifier: Programming Language :: Python :: 3.8
Classifier: Programming Language :: Python :: 3.9
Classifier: Programming Language :: Python :: 3.10
Classifier: Programming Language :: Python :: 3.11
Classifier: Programming Language :: Python :: 3.12
Classifier: Programming Language :: Python :: 3.13
Classifier: Topic :: Internet
Classifier: Topic :: Internet :: WWW/HTTP :: Session
Classifier: Topic :: Software Development :: Libraries :: Python Modules
Classifier: Typing :: Typed
Requires-Python: >=3.8
Requires-Dist: authx<2.0.0,>=1.1.0
Requires-Dist: prometheus-client<1.0.0,>=0.16.0
Requires-Dist: pyinstrument<5.1.0,>=4.1.1
Requires-Dist: redis<5.1.2,>=5.0.7
